{
    "data": {
      "msg": "Question Submitted Successfully",
      "result": {
        "mispronunciations": [
          "7",
          "30",
          "31",
          "56"
        ],
        "monotones": [
          "2", 
          "3", 
          "4", 
          "32",
          "35",
          "43",
          "44", 
          "45", 
          "46", 
          "47",
          "45",
          "52"
        ],
        "unexpectedBreaks": [
          "9",
          "18",
          "32",
          "35",
          "43",
          "45",
          "52",
          "56"
        ],
        "missingBreaks": [
          "1",
          "46",
          "53"
        ],
        "totalPhrase": [
          {
            "0": "Loading...."
          },
          {
            "1": "my"
          },
          {
            "2": "name"
          },
          {
            "3": "is"
          },
          {
            "4": "is"
          },
          {
            "5": "not"
          },
          {
            "6": "done"
          },
          {
            "7": "well"
          },
          {
            "8": "ma'am"
          },
          {
            "9": "there"
          },
          {
            "10": "are"
          },
          {
            "11": "many"
          },
          {
            "12": "ways"
          },
          {
            "13": "to"
          },
          {
            "14": "live"
          },
          {
            "15": "in"
          },
          {
            "16": "this"
          },
          {
            "17": "world"
          },
          {
            "18": "there"
          },
          {
            "19": "are"
          },
          {
            "20": "some"
          },
          {
            "21": "ways"
          },
          {
            "22": "like"
          },
          {
            "23": "a"
          },
          {
            "24": "doing"
          },
          {
            "25": "programming"
          },
          {
            "26": "god"
          },
          {
            "27": "doing"
          },
          {
            "28": "uh"
          },
          {
            "29": "some"
          },
          {
            "30": "natural"
          },
          {
            "31": "birth"
          },
          {
            "32": "and"
          },
          {
            "33": "playing"
          },
          {
            "34": "games"
          },
          {
            "35": "in"
          },
          {
            "36": "this"
          },
          {
            "37": "way"
          },
          {
            "38": "there"
          },
          {
            "39": "are"
          },
          {
            "40": "many"
          },
          {
            "41": "types"
          },
          {
            "42": "of"
          },
          {
            "43": "doing"
          },
          {
            "44": "things"
          },
          {
            "45": "so"
          },
          {
            "46": "i"
          },
          {
            "47": "want"
          },
          {
            "48": "to"
          },
          {
            "49": "be"
          },
          {
            "50": "a"
          },
          {
            "51": "programmer"
          },
          {
            "52": "because"
          },
          {
            "53": "i"
          },
          {
            "54": "like"
          },
          {
            "55": "it"
          },
          {
            "56": "OK"
          }
        ],
        "contentAssessment": {
          "GrammarScore": 58,
          "VocabularyScore": 60,
          "TopicScore": 76
        },
        "pronunciationAssessment": {
          "AccuracyScore": 94,
          "FluencyScore": 82,
          "ProsodyScore": 74.4,
          "CompletenessScore": 100,
          "PronScore": 79.8
        }
      }
    }
  }